tornado_xmlrpc/__init__.py
tornado_xmlrpc/client.py
tornado_xmlrpc/common.py
tornado_xmlrpc/handler.py
tornado_xmlrpc/xmlrpc.xsd
tornado_xmlrpc-1.0.dist-info/DESCRIPTION.rst
tornado_xmlrpc-1.0.dist-info/METADATA
tornado_xmlrpc-1.0.dist-info/RECORD
tornado_xmlrpc-1.0.dist-info/WHEEL
tornado_xmlrpc-1.0.dist-info/metadata.json
tornado_xmlrpc-1.0.dist-info/top_level.txt
