Metadata-Version: 2.0
Name: tornado-xmlrpc
Version: 1.0
Summary: Tornado XML-RPC server and client
Home-page: UNKNOWN
Author: Dmitry Orlov <me@mosquito.su>
Author-email: UNKNOWN
License: MIT
Platform: all
Classifier: Environment :: Console
Classifier: Programming Language :: Python :: 2
Classifier: Programming Language :: Python :: 2.7
Classifier: Programming Language :: Python :: 3
Classifier: Programming Language :: Python :: 3.2
Classifier: Programming Language :: Python :: 3.4
Classifier: Programming Language :: Python :: 3.5
Requires-Dist: lxml
Requires-Dist: slimurl
Requires-Dist: tornado (>=4.1)
